llama_index/voice_agents/openai/__init__.py
llama_index/voice_agents/openai/audio_interface.py
llama_index/voice_agents/openai/base.py
llama_index/voice_agents/openai/types.py
llama_index/voice_agents/openai/utils.py
llama_index/voice_agents/openai/websocket.py
llama_index_voice_agents_openai-0.2.1.dist-info/METADATA
llama_index_voice_agents_openai-0.2.1.dist-info/WHEEL
llama_index_voice_agents_openai-0.2.1.dist-info/licenses/LICENSE
llama_index_voice_agents_openai-0.2.1.dist-info/RECORD
