Metadata-Version: 2.4
Name: llama-index-voice-agents-openai
Version: 0.2.1
Summary: LlamaIndex x OpenAI Realtime integration
Author-email: Clelia Astra Bertelli <clelia@runllama.ai>
Maintainer: AstraBert
License-Expression: MIT
License-File: LICENSE
Requires-Python: <4.0,>=3.9
Requires-Dist: llama-index-core<0.15,>=0.13.0
Requires-Dist: pyaudio<0.3,>=0.2.14
Requires-Dist: websockets<16,>=15.0.1
